odoo/addons/sale_blanket_order_reference/LICENSE
odoo/addons/sale_blanket_order_reference/README.rst
odoo/addons/sale_blanket_order_reference/__init__.py
odoo/addons/sale_blanket_order_reference/__manifest__.py
odoo/addons/sale_blanket_order_reference/images/screen.png
odoo/addons/sale_blanket_order_reference/static/description/icon.png
odoo/addons/sale_blanket_order_reference/static/description/index.html
odoo/addons/sale_blanket_order_reference/wizard/__init__.py
odoo/addons/sale_blanket_order_reference/wizard/create_sale_orders.py
odoo_addon_sale_blanket_order_reference-16.0.1.0.0.dist-info/METADATA
odoo_addon_sale_blanket_order_reference-16.0.1.0.0.dist-info/WHEEL
odoo_addon_sale_blanket_order_reference-16.0.1.0.0.dist-info/top_level.txt
odoo_addon_sale_blanket_order_reference-16.0.1.0.0.dist-info/RECORD
